[
 {
    "title": "бһ–бҹ’бһҡбҹҮвҖҢбһҷбҹҒбһҹбҹҠбһјбһңвҖӢбһҳбһ¶бһ“вҖӢбһ”бһ“бҹ’бһ‘бһјбһӣвҖӢбһҶбҹ’бһӣбһҫбһҷвҖӢбһҗбһ¶ бһҳбһ·бһ“вҖӢбһҳбҹӮбһ“вҖӢбһҠбҹ„бһҷвҖӢбһ–бҹ’бһҡбҹ„бҹҮвҖӢбһўбҹ’бһ“бһҖвҖӢбһ“бҹҒбҹҮ бһ¬вҖӢбһӘбһ–бһ»бһҖвҖӢбһҳбҹ’бһҸбһ¶бһҷвҖӢбһӮбһ¶бһҸбҹӢвҖӢбһ”бһ¶бһ“вҖӢбһ’бҹ’бһңбһҫвҖӢбһ”бһ¶бһ”вҖӢбһ‘бҹҒ бһӮбһәвҖӢбһҠбһҫбһҳбҹ’бһ”бһёвҖӢбһІбҹ’бһҷвҖӢбһҖбһ¶бһҡвҖӢбһҡбһ”бһҹбҹӢвҖӢбһ–бҹ’бһҡбҹҮ бһ”бһ¶бһ“вҖӢбһҹбҹҶбһҠбҹӮбһ„вҖӢбһҳбһҖ бһҖбҹ’бһ“бһ»бһ„вҖӢбһҒбҹ’бһӣбһҪбһ“вҖӢбһӮбһ¶бһҸбҹӢвҖӢбһңбһ·бһү",
    "preacher": "Pastor Samnang",
    "subtitle": "Wednesday Worship Sermon",
    "date": "2026-01-28",
    "file": "бһӮбһәвҖӢбһҠбһҫбһҳбҹ’бһ”бһёвҖӢбһІбҹ’бһҷвҖӢбһҖбһ¶бһҡвҖӢбһҡбһ”бһҹбҹӢвҖӢбһ–бҹ’бһҡбҹҮбһ”бһ¶бһ“вҖӢбһҹбҹҶбһҠбҹӮбһ„вҖӢбһҳбһҖбһҖбҹ’бһ“бһ»бһ„вҖӢбһҒбҹ’бһӣбһҪбһ“вҖӢбһӮбһ¶бһҸбҹӢвҖӢбһңбһ·бһү"
  },
 
 {
    "title": "бһӣбҹ„бһҖбһ»бһ”бҹ’бһ”бһҸбҹ’бһҸбһ· 35:1-5 бһ…бһјбһҡвҖӢбһҡбҹҖбһ”бһ…бҹҶвҖӢбһЎбһҫбһ„вҖӢбһ‘бҹ…вҖӢбһҜвҖӢбһ”бҹҒбһҸ-бһўбҹӮбһӣ",
    "preacher": "Pastor David Mengtong",
    "subtitle": "Monday Worship Sermon",
    "date": "2026-02-23",
    "file": "бһӣбҹ„бһҖбһ»бһ”бҹ’бһ”бһҸбҹ’бһҸбһ· 35-бһ…бһјбһҡвҖӢбһҡбҹҖбһ”бһ…бҹҶвҖӢбһЎбһҫбһ„вҖӢбһ‘бҹ…вҖӢбһҜвҖӢбһ”бҹҒбһҸ-бһўбҹӮбһӣ"
  },
 {
    "title": "бһўбҹҶбһ–бһ¶бһңбһ“бһ¶бһңбһ“бҹ„бҹҮбһ–бҹ’бһҡбҹҮбһ“бһ№бһ„бһҶбҹ’бһӣбһҫбһҷбһҸбһ”",
    "preacher": "Pastor Kim Changyoung",
    "subtitle": "Monday Worship Sermon",
    "date": "2026-03-03",
    "file": "бһўбҹҶбһ–бһ¶бһңбһ“бһ¶бһңбһ“бҹ„бҹҮбһ–бҹ’бһҡбҹҮбһ“бһ№бһ„бһҶбҹ’бһӣбһҫбһҷбһҸбһ”"
  },
 {
    "title": "бһҸбһҫбһІбҹ’бһҷбһҒбҹ’бһүбһ»бҹҶбһ’бҹ’бһңбһҫбһўбҹ’бһңбһёбһҹбҹҶбһҡбһ¶бһ”бҹӢбһ–бҹ’бһҡбҹҮбһҷбҹҒбһҹбҹҠбһјбһң?",
    "preacher": "Pastor Mary",
    "subtitle": "Sunday Worship Sermon",
    "date": "2026-03-29",
    "file": "бһҸбһҫбһІбҹ’бһҷбһҒбҹ’бһүбһ»бҹҶбһ’бҹ’бһңбһҫбһўбҹ’бһңбһёбһҹбҹҶбһҡбһ¶бһ”бҹӢбһ–бҹ’бһҡбҹҮбһҷбҹҒбһҹбҹҠбһјбһң"
  },
  {
    "title": "бһ–бҹ’бһҡбҹҮбһңбһ·бһүбҹ’бһүбһ¶бһҺбһ–бҹ’бһҡбҹҮбһўбһҳбҹ’бһ…бһ¶бһҹбҹӢбһҹбһ“бҹ’бһҗбһ·бһҸбһӣбһҫбһҒбҹ’бһүбһ»бҹҶ",
    "preacher": "Pastor Nop Phearun",
    "subtitle": "Monday Worship Sermon",
    "date": "2026-03-23",
    "file": "бһ–бҹ’бһҡбҹҮбһңбһ·бһүбҹ’бһүбһ¶бһҺбһ–бҹ’бһҡбҹҮбһўбһҳбҹ’бһ…бһ¶бһҹбҹӢбһҹбһ“бҹ’бһҗбһ·бһҸбһӣбһҫбһҒбҹ’бһүбһ»бҹҶ"
  },
  {
    "title": "Here I am to Worship",
    "preacher": "Music Instrument",
    "subtitle": "Worship Song",
    "date": "2026-03-24",
    "file": "here-i-am-to-worship"
  },
  {
    "title": "",
    "preacher": "Pastor ",
    "subtitle": "Morning Message",
    "date": "",
    "file": ""
  },
  
  {
    "title": "бһ”бһ»бһҺбҹ’бһҷбһҖбһ¶бһ“бҹӢбһ‘бһ»бһҖбҹ’бһҒбһҒбҹ’бһүбһ»бҹҶбһӮбһҪбһҡбһҹбҹӢбһ“бҹ…бһҷбҹүбһ¶бһ„бһҺбһ¶?",
    "preacher": "Pastor Marry",
    "subtitle": "Sunday Worship Sermon",
    "date": "2026-03-22",
    "file": "бһ”бһ»бһҺбҹ’бһҷбһҖбһ¶бһ“бҹӢбһ‘бһ»бһҖбҹ’бһҒбһҒбҹ’бһүбһ»бҹҶбһӮбһҪбһҡбһҹбҹӢбһ“бҹ…бһҷбҹүбһ¶бһ„бһҺбһ¶"
  },
  {
    "title": "бһҖбһ»бҹҶбһҡбһҹбһ¶бһҷбһ…бһ·бһҸбҹ’бһҸбһЎбһҫбһҷ",
    "preacher": "Pastor Marry",
    "subtitle": "Sunday Worship Sermon",
    "date": "2022-11-06",
    "file": "бһҖбһ»бҹҶбһҡбһҹбһ¶бһҷбһ…бһ·бһҸбҹ’бһҸбһЎбһҫбһҷ"
  },
  {
    "title": "бһҹбһјбһҳвҖӢбһІбҹ’бһҷвҖӢбһҹбҹ’бһҡбһ»бһҖвҖӢбһ—бҹ’бһ“бҹҶвҖӢбһ“бҹҒбҹҮбһҳбһҖвҖӢбһҒбҹ’бһүбһ»бҹҶ",
    "preacher": "Pastor Marry",
    "subtitle": "Sunday Worship Sermon",
    "date": "2022-11-20",
    "file": "бһҹбһјбһҳвҖӢбһІбҹ’бһҷвҖӢбһҹбҹ’бһҡбһ»бһҖвҖӢбһ—бҹ’бһ“бҹҶвҖӢбһ“бҹҒбҹҮбһҳбһҖвҖӢбһҒбҹ’бһүбһ»бҹҶвҖӢ"
  },
 {
    "file": "sermon001",
    "title": "Test Sermon",
    "preacher": "Pastor Name",
    "subtitle": "Sunday Message",
    "date": "2026-04-02",
    "audioUrl": "https://thythet.ct.ws/wp-content/uploads/2026/04/sermon001.mp3"
  }
]
